mms-alice-python-logger_pkg/__init__.py
mms-alice-python-logger_pkg/alice_log_handler.py
mms_alice_python_logger_pkg/__init__.py
mms_alice_python_logger_pkg/alice_log_handler.py
mms_python_logger-0.0.4.dist-info/LICENSE
mms_python_logger-0.0.4.dist-info/METADATA
mms_python_logger-0.0.4.dist-info/WHEEL
mms_python_logger-0.0.4.dist-info/top_level.txt
mms_python_logger-0.0.4.dist-info/RECORD
