Metadata-Version: 2.1
Name: mms-python-logger
Version: 0.0.4
Summary: A custom MMS/Alice log module for python
Home-page: https://github.com/EastOfGondor/mms-alice-python-logger
Author: Tobias hoke
Author-email: hoke@mediamarktsaturn.com
License: UNKNOWN
Platform: UNKNOWN
Classifier: Programming Language :: Python :: 3
Classifier: License :: OSI Approved :: MIT License
Classifier: Operating System :: OS Independent
